[{"country_name":"Timor-Leste","year":2016,"earth_footprint":0.3044,"all":1.841},{"country_name":"Eritrea","year":2016,"earth_footprint":0.3075,"all":1.841},{"country_name":"Burundi","year":2016,"earth_footprint":0.4038,"all":1.841},{"country_name":"Yemen","year":2016,"earth_footprint":0.4108,"all":1.841},{"country_name":"Haiti","year":2016,"earth_footprint":0.4144,"all":1.841},{"country_name":"Eritrea","year":2015,"earth_footprint":0.3064,"all":1.8719},{"country_name":"Timor-Leste","year":2015,"earth_footprint":0.3208,"all":1.8719},{"country_name":"Burundi","year":2015,"earth_footprint":0.3928,"all":1.8719},{"country_name":"Haiti","year":2015,"earth_footprint":0.4185,"all":1.8719},{"country_name":"Yemen","year":2015,"earth_footprint":0.4334,"all":1.8719},{"country_name":"Eritrea","year":2014,"earth_footprint":0.312,"all":1.9008},{"country_name":"Timor-Leste","year":2014,"earth_footprint":0.3453,"all":1.9008},{"country_name":"Burundi","year":2014,"earth_footprint":0.3948,"all":1.9008},{"country_name":"Haiti","year":2014,"earth_footprint":0.3949,"all":1.9008},{"country_name":"Afghanistan","year":2014,"earth_footprint":0.4538,"all":1.9008},{"country_name":"Eritrea","year":2013,"earth_footprint":0.3248,"all":2.0411},{"country_name":"Haiti","year":2013,"earth_footprint":0.4014,"all":2.0411},{"country_name":"Burundi","year":2013,"earth_footprint":0.4218,"all":2.0411},{"country_name":"Timor-Leste","year":2013,"earth_footprint":0.4402,"all":2.0411},{"country_name":"Afghanistan","year":2013,"earth_footprint":0.4528,"all":2.0411},{"country_name":"Timor-Leste","year":2012,"earth_footprint":0.2843,"all":1.8181},{"country_name":"Eritrea","year":2012,"earth_footprint":0.3294,"all":1.8181},{"country_name":"Haiti","year":2012,"earth_footprint":0.3696,"all":1.8181},{"country_name":"Burundi","year":2012,"earth_footprint":0.3889,"all":1.8181},{"country_name":"Bangladesh","year":2012,"earth_footprint":0.4459,"all":1.8181},{"country_name":"Timor-Leste","year":2011,"earth_footprint":0.2411,"all":1.8668},{"country_name":"Eritrea","year":2011,"earth_footprint":0.3374,"all":1.8668},{"country_name":"Haiti","year":2011,"earth_footprint":0.381,"all":1.8668},{"country_name":"Bangladesh","year":2011,"earth_footprint":0.4536,"all":1.8668},{"country_name":"Afghanistan","year":2011,"earth_footprint":0.4537,"all":1.8668},{"country_name":"Timor-Leste","year":2010,"earth_footprint":0.2598,"all":1.8782},{"country_name":"Eritrea","year":2010,"earth_footprint":0.3333,"all":1.8782},{"country_name":"Haiti","year":2010,"earth_footprint":0.3886,"all":1.8782},{"country_name":"Bangladesh","year":2010,"earth_footprint":0.4335,"all":1.8782},{"country_name":"Afghanistan","year":2010,"earth_footprint":0.4631,"all":1.8782},{"country_name":"Timor-Leste","year":2009,"earth_footprint":0.2857,"all":1.8411},{"country_name":"Eritrea","year":2009,"earth_footprint":0.3365,"all":1.8411},{"country_name":"Haiti","year":2009,"earth_footprint":0.3659,"all":1.8411},{"country_name":"Bangladesh","year":2009,"earth_footprint":0.4051,"all":1.8411},{"country_name":"Afghanistan","year":2009,"earth_footprint":0.448,"all":1.8411},{"country_name":"Timor-Leste","year":2008,"earth_footprint":0.237,"all":1.6546},{"country_name":"Eritrea","year":2008,"earth_footprint":0.3201,"all":1.6546},{"country_name":"Haiti","year":2008,"earth_footprint":0.3433,"all":1.6546},{"country_name":"Afghanistan","year":2008,"earth_footprint":0.3758,"all":1.6546},{"country_name":"Bangladesh","year":2008,"earth_footprint":0.3784,"all":1.6546},{"country_name":"Timor-Leste","year":2007,"earth_footprint":0.2736,"all":1.7951},{"country_name":"Haiti","year":2007,"earth_footprint":0.3543,"all":1.7951},{"country_name":"Bangladesh","year":2007,"earth_footprint":0.3767,"all":1.7951},{"country_name":"Afghanistan","year":2007,"earth_footprint":0.3873,"all":1.7951},{"country_name":"Rwanda","year":2007,"earth_footprint":0.4031,"all":1.7951},{"country_name":"Timor-Leste","year":2006,"earth_footprint":0.2764,"all":1.7228},{"country_name":"Haiti","year":2006,"earth_footprint":0.3382,"all":1.7228},{"country_name":"Bangladesh","year":2006,"earth_footprint":0.3557,"all":1.7228},{"country_name":"Afghanistan","year":2006,"earth_footprint":0.3592,"all":1.7228},{"country_name":"Rwanda","year":2006,"earth_footprint":0.3931,"all":1.7228},{"country_name":"Timor-Leste","year":2005,"earth_footprint":0.278,"all":1.6743},{"country_name":"Haiti","year":2005,"earth_footprint":0.3314,"all":1.6743},{"country_name":"Bangladesh","year":2005,"earth_footprint":0.3374,"all":1.6743},{"country_name":"Malawi","year":2005,"earth_footprint":0.3501,"all":1.6743},{"country_name":"Rwanda","year":2005,"earth_footprint":0.3774,"all":1.6743},{"country_name":"Timor-Leste","year":2004,"earth_footprint":0.2758,"all":1.628},{"country_name":"Bangladesh","year":2004,"earth_footprint":0.318,"all":1.628},{"country_name":"Haiti","year":2004,"earth_footprint":0.3265,"all":1.628},{"country_name":"Afghanistan","year":2004,"earth_footprint":0.3296,"all":1.628},{"country_name":"Rwanda","year":2004,"earth_footprint":0.3782,"all":1.628},{"country_name":"Timor-Leste","year":2003,"earth_footprint":0.2719,"all":1.6814},{"country_name":"Haiti","year":2003,"earth_footprint":0.3195,"all":1.6814},{"country_name":"Bangladesh","year":2003,"earth_footprint":0.3212,"all":1.6814},{"country_name":"Afghanistan","year":2003,"earth_footprint":0.3842,"all":1.6814},{"country_name":"Rwanda","year":2003,"earth_footprint":0.3847,"all":1.6814},{"country_name":"Timor-Leste","year":2002,"earth_footprint":0.2849,"all":1.6817},{"country_name":"Bangladesh","year":2002,"earth_footprint":0.315,"all":1.6817},{"country_name":"Haiti","year":2002,"earth_footprint":0.316,"all":1.6817},{"country_name":"Afghanistan","year":2002,"earth_footprint":0.3804,"all":1.6817},{"country_name":"Malawi","year":2002,"earth_footprint":0.3854,"all":1.6817},{"country_name":"Timor-Leste","year":2001,"earth_footprint":0.2867,"all":1.5979},{"country_name":"Haiti","year":2001,"earth_footprint":0.2996,"all":1.5979},{"country_name":"Bangladesh","year":2001,"earth_footprint":0.3105,"all":1.5979},{"country_name":"Afghanistan","year":2001,"earth_footprint":0.3212,"all":1.5979},{"country_name":"Rwanda","year":2001,"earth_footprint":0.3798,"all":1.5979},{"country_name":"Timor-Leste","year":2000,"earth_footprint":0.293,"all":1.6249},{"country_name":"Bangladesh","year":2000,"earth_footprint":0.3043,"all":1.6249},{"country_name":"Haiti","year":2000,"earth_footprint":0.3117,"all":1.6249},{"country_name":"Afghanistan","year":2000,"earth_footprint":0.3411,"all":1.6249},{"country_name":"Rwanda","year":2000,"earth_footprint":0.3749,"all":1.6249},{"country_name":"Timor-Leste","year":1999,"earth_footprint":0.2726,"all":1.635},{"country_name":"Bangladesh","year":1999,"earth_footprint":0.301,"all":1.635},{"country_name":"Haiti","year":1999,"earth_footprint":0.3253,"all":1.635},{"country_name":"Angola","year":1999,"earth_footprint":0.3537,"all":1.635},{"country_name":"Afghanistan","year":1999,"earth_footprint":0.3824,"all":1.635},{"country_name":"Timor-Leste","year":1998,"earth_footprint":0.263,"all":1.582},{"country_name":"Bangladesh","year":1998,"earth_footprint":0.272,"all":1.582},{"country_name":"Haiti","year":1998,"earth_footprint":0.3171,"all":1.582},{"country_name":"Angola","year":1998,"earth_footprint":0.3574,"all":1.582},{"country_name":"Afghanistan","year":1998,"earth_footprint":0.3725,"all":1.582},{"country_name":"Bangladesh","year":1997,"earth_footprint":0.2657,"all":1.5646},{"country_name":"Timor-Leste","year":1997,"earth_footprint":0.2786,"all":1.5646},{"country_name":"Haiti","year":1997,"earth_footprint":0.3196,"all":1.5646},{"country_name":"Angola","year":1997,"earth_footprint":0.3405,"all":1.5646},{"country_name":"Afghanistan","year":1997,"earth_footprint":0.3603,"all":1.5646},{"country_name":"Bangladesh","year":1996,"earth_footprint":0.2581,"all":1.5322},{"country_name":"Timor-Leste","year":1996,"earth_footprint":0.2889,"all":1.5322},{"country_name":"Haiti","year":1996,"earth_footprint":0.3056,"all":1.5322},{"country_name":"Angola","year":1996,"earth_footprint":0.3363,"all":1.5322},{"country_name":"Afghanistan","year":1996,"earth_footprint":0.3434,"all":1.5322},{"country_name":"Bangladesh","year":1995,"earth_footprint":0.2493,"all":1.5104},{"country_name":"Timor-Leste","year":1995,"earth_footprint":0.2919,"all":1.5104},{"country_name":"Haiti","year":1995,"earth_footprint":0.3053,"all":1.5104},{"country_name":"Angola","year":1995,"earth_footprint":0.3311,"all":1.5104},{"country_name":"Afghanistan","year":1995,"earth_footprint":0.3328,"all":1.5104},{"country_name":"Bangladesh","year":1994,"earth_footprint":0.2332,"all":1.4623},{"country_name":"Haiti","year":1994,"earth_footprint":0.2671,"all":1.4623},{"country_name":"Timor-Leste","year":1994,"earth_footprint":0.2913,"all":1.4623},{"country_name":"Afghanistan","year":1994,"earth_footprint":0.3293,"all":1.4623},{"country_name":"Malawi","year":1994,"earth_footprint":0.3413,"all":1.4623},{"country_name":"Bangladesh","year":1993,"earth_footprint":0.2365,"all":1.5056},{"country_name":"Haiti","year":1993,"earth_footprint":0.2861,"all":1.5056},{"country_name":"Timor-Leste","year":1993,"earth_footprint":0.2998,"all":1.5056},{"country_name":"Afghanistan","year":1993,"earth_footprint":0.3412,"all":1.5056},{"country_name":"Angola","year":1993,"earth_footprint":0.342,"all":1.5056},{"country_name":"Bangladesh","year":1992,"earth_footprint":0.2392,"all":1.4901},{"country_name":"Timor-Leste","year":1992,"earth_footprint":0.2801,"all":1.4901},{"country_name":"Haiti","year":1992,"earth_footprint":0.292,"all":1.4901},{"country_name":"Malawi","year":1992,"earth_footprint":0.3308,"all":1.4901},{"country_name":"Afghanistan","year":1992,"earth_footprint":0.348,"all":1.4901},{"country_name":"Bangladesh","year":1991,"earth_footprint":0.2343,"all":1.5146},{"country_name":"Haiti","year":1991,"earth_footprint":0.2813,"all":1.5146},{"country_name":"Timor-Leste","year":1991,"earth_footprint":0.298,"all":1.5146},{"country_name":"Malawi","year":1991,"earth_footprint":0.346,"all":1.5146},{"country_name":"Viet Nam","year":1991,"earth_footprint":0.355,"all":1.5146},{"country_name":"Bangladesh","year":1990,"earth_footprint":0.2361,"all":1.4856},{"country_name":"Haiti","year":1990,"earth_footprint":0.2832,"all":1.4856},{"country_name":"Timor-Leste","year":1990,"earth_footprint":0.2851,"all":1.4856},{"country_name":"Malawi","year":1990,"earth_footprint":0.3369,"all":1.4856},{"country_name":"Viet Nam","year":1990,"earth_footprint":0.3444,"all":1.4856}]
